{
  "Cities I've been to": [
    {
      "Title": "Haifa",
      "Country": "Israel",
      "Period": "1 month",
      "Year": "2017"
    },
    {
      "Title": "Vancouver",
      "Country": "Canada",
      "Period": "1 month",
      "Year": "2016"
    },
    {
      "Title": "Manila",
      "Country": "Philippines",
      "Period": "3 month",
      "Year": "2020"
    },
    {
      "Title": "Berkeley",
      "Country": "Unitied States",
      "Period": "3 month",
      "Year": "2024"
    }
  ]
}
